CHANGES.rst
CONTRIBUTORS.rst
DEVELOP.rst
LICENSE.rst
MANIFEST.in
README.rst
setup.cfg
setup.py
docs/conf.so
docs/index.rst
src/collective/__init__.py
src/collective.ant.egg-info/PKG-INFO
src/collective.ant.egg-info/SOURCES.txt
src/collective.ant.egg-info/dependency_links.txt
src/collective.ant.egg-info/entry_points.txt
src/collective.ant.egg-info/namespace_packages.txt
src/collective.ant.egg-info/not-zip-safe
src/collective.ant.egg-info/requires.txt
src/collective.ant.egg-info/top_level.txt
src/collective/ant/__init__.py
src/collective/ant/configure.zcml
src/collective/ant/converter.so
src/collective/ant/events.so
src/collective/ant/handlers.so
src/collective/ant/interfaces.pyc
src/collective/ant/permissions.zcml
src/collective/ant/setuphandlers.pyc
src/collective/ant/testing.so
src/collective/ant/upgrades.so
src/collective/ant/upgrades.zcml
src/collective/ant/utils.so
src/collective/ant/validate.so
src/collective/ant/adapters/__init__.py
src/collective/ant/adapters/anything.so
src/collective/ant/adapters/configure.zcml
src/collective/ant/adapters/stringinterp.so
src/collective/ant/browser/__init__.py
src/collective/ant/browser/configure.zcml
src/collective/ant/browser/content_view.so
src/collective/ant/browser/controlpanel.so
src/collective/ant/browser/export.so
src/collective/ant/browser/form.pyc
src/collective/ant/browser/import_data.so
src/collective/ant/browser/jsonrpc.so
src/collective/ant/browser/schedule.so
src/collective/ant/browser/schedule.zcml
src/collective/ant/browser/tools.so
src/collective/ant/browser/validator.so
src/collective/ant/browser/validator.zcml
src/collective/ant/browser/versioning.so
src/collective/ant/browser/overrides/.gitkeep
src/collective/ant/browser/static/.gitkeep
src/collective/ant/browser/static/ant.css
src/collective/ant/browser/static/ant.js
src/collective/ant/browser/static/boilerplate.js
src/collective/ant/browser/static/main.js
src/collective/ant/browser/templates/content_view.pt
src/collective/ant/browser/templates/controlpanel.pt
src/collective/ant/browser/templates/help.pt
src/collective/ant/browser/templates/import_data.pt
src/collective/ant/browser/templates/navigation.pt
src/collective/ant/browser/templates/stringinterp.pt
src/collective/ant/content/__init__.py
src/collective/ant/content/ant_base.xml
src/collective/ant/locales/README.rst
